pulumiverse_cockroach/__init__.py
pulumiverse_cockroach/_inputs.py
pulumiverse_cockroach/_utilities.py
pulumiverse_cockroach/allow_list.py
pulumiverse_cockroach/api_key.py
pulumiverse_cockroach/ca_cert.py
pulumiverse_cockroach/cluster.py
pulumiverse_cockroach/cmek.py
pulumiverse_cockroach/database.py
pulumiverse_cockroach/finalize_version_upgrade.py
pulumiverse_cockroach/folder.py
pulumiverse_cockroach/get_cluster_cert.py
pulumiverse_cockroach/get_cockroach_cluster.py
pulumiverse_cockroach/get_connection_string.py
pulumiverse_cockroach/get_folder.py
pulumiverse_cockroach/get_organization.py
pulumiverse_cockroach/get_person_user.py
pulumiverse_cockroach/jwt_issuer.py
pulumiverse_cockroach/log_export_config.py
pulumiverse_cockroach/maintenance_window.py
pulumiverse_cockroach/metric_export_cloudwatch_config.py
pulumiverse_cockroach/metric_export_datadog_config.py
pulumiverse_cockroach/metric_export_prometheus_config.py
pulumiverse_cockroach/outputs.py
pulumiverse_cockroach/private_endpoint_connection.py
pulumiverse_cockroach/private_endpoint_services.py
pulumiverse_cockroach/private_endpoint_trusted_owner.py
pulumiverse_cockroach/provider.py
pulumiverse_cockroach/pulumi-plugin.json
pulumiverse_cockroach/py.typed
pulumiverse_cockroach/service_account.py
pulumiverse_cockroach/sql_user.py
pulumiverse_cockroach/user_role_grant.py
pulumiverse_cockroach/user_role_grants.py
pulumiverse_cockroach/version_deferral.py
pulumiverse_cockroach/config/__init__.py
pulumiverse_cockroach/config/__init__.pyi
pulumiverse_cockroach/config/vars.py
pulumiverse_cockroach-0.9.4.dist-info/METADATA
pulumiverse_cockroach-0.9.4.dist-info/WHEEL
pulumiverse_cockroach-0.9.4.dist-info/top_level.txt
pulumiverse_cockroach-0.9.4.dist-info/RECORD
