Metadata-Version: 2.4
Name: pulumiverse_cockroach
Version: 0.9.4
Summary: A Pulumi package to create and managed Cockroach DB resources in Pulumi programs.
License: Apache-2.0
Project-URL: Homepage, https://www.cockroachlabs.com/
Project-URL: Repository, https://github.com/pulumiverse/pulumi-cockroach
Keywords: pulumi,cockroach,pulumiverse
Requires-Python: >=3.9
Requires-Dist: parver>=0.2.1
Requires-Dist: pulumi<4.0.0,>=3.0.0
Requires-Dist: semver>=2.8.1
Requires-Dist: typing-extensions>=4.11; python_version < "3.11"
